{
  "date": "2025-03-16",
  "day_of_week": "Sunday",
  "activities": [
    {
      "activity_type": "leisure",
      "start_time": "05:26",
      "end_time": "07:06",
      "description": "Enjoyed reading and listening to music at home.",
      "location_name": "Home",
      "location_type": "home",
      "transport_mode": "No need to travel",
      "distance": 0,
      "travel_time": 0,
      "coordinates": [
        41.776951,
        -87.623216
      ]
    },
    {
      "activity_type": "dining",
      "start_time": "07:06",
      "end_time": "07:36",
      "description": "Prepared and had breakfast at home.",
      "location_name": "Home",
      "location_type": "home",
      "transport_mode": "No need to travel",
      "distance": 0,
      "travel_time": 0,
      "coordinates": [
        41.776951,
        -87.623216
      ]
    },
    {
      "activity_type": "errands",
      "start_time": "07:36",
      "end_time": "08:00",
      "description": "Quick trip to the bank for some transactions.",
      "location_name": "Bank",
      "location_type": "bank",
      "transport_mode": "walking",
      "distance": 0.11687466832341149,
      "travel_time": 3,
      "coordinates": [
        41.77722567430746,
        -87.62457303241831
      ]
    },
    {
      "activity_type": "shopping",
      "start_time": "08:00",
      "end_time": "08:43",
      "description": "Grocery shopping for the week at the local supermarket.",
      "location_name": "Grocery",
      "location_type": "grocery_store",
      "transport_mode": "walking",
      "distance": 0.27624699372700384,
      "travel_time": 5,
      "coordinates": [
        41.77953818322452,
        -87.62334984158385
      ]
    },
    {
      "activity_type": "leisure",
      "start_time": "08:43",
      "end_time": "10:43",
      "description": "Watched a movie at home and relaxed.",
      "location_name": "Home",
      "location_type": "home",
      "transport_mode": "walking",
      "distance": 0.287571161103077,
      "travel_time": 5,
      "coordinates": [
        41.776951,
        -87.623216
      ]
    },
    {
      "activity_type": "dining",
      "start_time": "10:43",
      "end_time": "11:13",
      "description": "Prepared and enjoyed a light lunch at home.",
      "location_name": "Home",
      "location_type": "home",
      "transport_mode": "No need to travel",
      "distance": 0,
      "travel_time": 0,
      "coordinates": [
        41.776951,
        -87.623216
      ]
    },
    {
      "activity_type": "recreation",
      "start_time": "11:13",
      "end_time": "12:13",
      "description": "Took a walk in the nearby park for exercise.",
      "location_name": "Neighborhood Walking Path",
      "location_type": "park",
      "transport_mode": "walking",
      "distance": 0.6541471981727595,
      "travel_time": 10,
      "coordinates": [
        41.77188090460316,
        -87.61921256961853
      ]
    },
    {
      "activity_type": "errands",
      "start_time": "12:13",
      "end_time": "12:37",
      "description": "Stopped at the post office to send a package.",
      "location_name": "The UPS Store",
      "location_type": "post_office",
      "transport_mode": "walking",
      "distance": 1.5294075076575209,
      "travel_time": 20,
      "coordinates": [
        41.7805882,
        -87.6049618
      ]
    }
  ]
}